epaswmm/CMakeLists.txt
epaswmm/__init__.py
epaswmm/_epaswmm.pyx
epaswmm/epaswmm.pxd
epaswmm/output/CMakeLists.txt
epaswmm/output/__init__.pxd
epaswmm/output/__init__.py
epaswmm/output/_output.pyi
epaswmm/output/_output.pyx
epaswmm/output/output.pxd
epaswmm/solver/CMakeLists.txt
epaswmm/solver/__init__.pxd
epaswmm/solver/__init__.py
epaswmm/solver/_solver.pyi
epaswmm/solver/_solver.pyx
epaswmm/solver/solver.pxd
epaswmm-5.3.0.dev9.dist-info/licenses/LICENSE
tests/__init__.py
tests/test_swmm_solver.py
tests/test_swwm_output.py
tests/data/__init__.py
tests/data/output/__init__.py
tests/data/output/example_output_1.out
tests/data/output/json_time_series.pickle
tests/data/solver/__init__.py
tests/data/solver/non_existent_input_file.rpt
tests/data/solver/site_drainage_example.inp
tests/data/solver/site_drainage_example.rpt
epaswmm-5.3.0.dev9.dist-info/METADATA
epaswmm-5.3.0.dev9.dist-info/WHEEL
epaswmm-5.3.0.dev9.dist-info/top_level.txt
epaswmm-5.3.0.dev9.dist-info/RECORD
