Metadata-Version: 2.1
Name: epaswmm
Version: 5.3.0.dev9
Summary: A python package for EPA SWMM5 preprocessing, solver, and post-processing.
Author-email: Caleb Buahin <buahin.caleb@epa.gov>
Maintainer-email: Caleb Buahin <buahin.caleb@epa.gov>
License: Creative Commons Legal Code
Project-URL: Homepage, https://github.com/USEPA/Stormwater-Management-Model
Project-URL: Documentation, https://github.com/USEPA/Stormwater-Management-Model
Project-URL: Source Code, https://github.com/USEPA/Stormwater-Management-Model
Project-URL: Bug Tracker, https://github.com/USEPA/Stormwater-Management-Model/issues
Project-URL: Repository, https://github.com/USEPA/Stormwater-Management-Model
Project-URL: Changelog, https://github.com/USEPA/Stormwater-Management-Model/blob/master/CHANGELOG.md
Keywords: SWMM,stormwater,modeling,water,hydrology,hydraulics,wastewater
Classifier: Development Status :: 3 - Alpha
Classifier: Intended Audience :: Developers
Classifier: Intended Audience :: Science/Research
Classifier: Operating System :: OS Independent
Classifier: Programming Language :: Python :: 3.8
Classifier: Programming Language :: Python :: 3.9
Classifier: Programming Language :: Python :: 3.10
Classifier: Programming Language :: Python :: 3.11
Classifier: Programming Language :: Python :: 3.12
Classifier: Programming Language :: Python :: 3.13
Classifier: Programming Language :: C
Classifier: Programming Language :: Cython
Classifier: Programming Language :: C++
Classifier: Topic :: Scientific/Engineering
Classifier: Topic :: Scientific/Engineering :: Hydrology
Classifier: Topic :: Scientific/Engineering :: Mathematics
Classifier: Topic :: Scientific/Engineering :: Physics
Classifier: Topic :: Software Development :: Libraries
Classifier: Topic :: Software Development :: Libraries :: Python Modules
Classifier: Topic :: Scientific/Engineering :: GIS
Classifier: Development Status :: 3 - Alpha
Requires-Python: >=3.8
License-File: LICENSE
